fds/__init__.py
fds/sdk/__init__.py
fds/sdk/ExchangeDataFeedDataModel/__init__.py
fds/sdk/ExchangeDataFeedDataModel/api_client.py
fds/sdk/ExchangeDataFeedDataModel/configuration.py
fds/sdk/ExchangeDataFeedDataModel/exceptions.py
fds/sdk/ExchangeDataFeedDataModel/model_utils.py
fds/sdk/ExchangeDataFeedDataModel/rest.py
fds/sdk/ExchangeDataFeedDataModel/api/__init__.py
fds/sdk/ExchangeDataFeedDataModel/api/exchange_information_api.py
fds/sdk/ExchangeDataFeedDataModel/api/product_codes_api.py
fds/sdk/ExchangeDataFeedDataModel/apis/__init__.py
fds/sdk/ExchangeDataFeedDataModel/model/__init__.py
fds/sdk/ExchangeDataFeedDataModel/model/error_detail.py
fds/sdk/ExchangeDataFeedDataModel/model/error_response.py
fds/sdk/ExchangeDataFeedDataModel/model/exchange_item.py
fds/sdk/ExchangeDataFeedDataModel/model/exchanges_response.py
fds/sdk/ExchangeDataFeedDataModel/model/exchanges_response_data.py
fds/sdk/ExchangeDataFeedDataModel/model/product_item.py
fds/sdk/ExchangeDataFeedDataModel/model/products_response.py
fds/sdk/ExchangeDataFeedDataModel/model/products_response_data.py
fds/sdk/ExchangeDataFeedDataModel/models/__init__.py
fds_sdk_exchangedatafeeddatamodel-0.21.0.dist-info/licenses/LICENSE
fds_sdk_exchangedatafeeddatamodel-0.21.0.dist-info/METADATA
fds_sdk_exchangedatafeeddatamodel-0.21.0.dist-info/WHEEL
fds_sdk_exchangedatafeeddatamodel-0.21.0.dist-info/top_level.txt
fds_sdk_exchangedatafeeddatamodel-0.21.0.dist-info/RECORD
